cmd_gui_kit/__init__.py
cmd_gui_kit/cmd_gui_kit.py
cmd_gui_kit-1.0.0.dist-info/LICENSE
cmd_gui_kit-1.0.0.dist-info/WHEEL
cmd_gui_kit-1.0.0.dist-info/METADATA
cmd_gui_kit-1.0.0.dist-info/RECORD
