Metadata-Version: 2.3
Name: cmd_gui_kit
Version: 1.0.0
Summary: cmd-gui-kit: A Python toolkit for enhanced CLI visualizations.
Author-email: cagatay-softgineer <cagatayalkan333@gmail.com>
Classifier: License :: OSI Approved :: MIT License
Project-URL: Home, https://github.com/cagatay-softgineer/cmd-gui-kit
